nops_kafka/__init__.py
nops_kafka-0.2.1.dist-info/WHEEL
nops_kafka-0.2.1.dist-info/METADATA
nops_kafka-0.2.1.dist-info/RECORD
